pybarm
