Metadata-Version: 1.0
Name: pybarm
Version: 0.0.0.4
Summary: code for controlling miscellaneous Raspberry Pi accessories
Home-page: http://github.com/danmaclean/pybarm
Author: Dan MacLean
Author-email: maclean.daniel@gmail.com
License: MIT
Platform: UNKNOWN
